sismis/__init__.py
sismis/__main__.py
sismis/cli.py
sismis/py.typed
sismis/crf/__init__.py
sismis/crf/model.pkl
sismis/crf/model.pkl.md5
sismis/hmmer/Pfam.h3m
sismis/hmmer/Pfam.ini
sismis/hmmer/__init__.py
sismis/types/__init__.py
sismis/types/compositions.npz
sismis/types/domains.tsv
sismis/types/types.tsv
sismis-0.1.1.dist-info/licenses/LICENSE
sismis-0.1.1.dist-info/METADATA
sismis-0.1.1.dist-info/WHEEL
sismis-0.1.1.dist-info/entry_points.txt
sismis-0.1.1.dist-info/top_level.txt
sismis-0.1.1.dist-info/RECORD
