Metadata-Version: 2.4
Name: sismis
Version: 0.1.1
Summary: Secretion system discovery tool.
Author-email: "Laura M. Carroll" <lmc297@cornell.edu>, Martin Larralde <martin.larralde@embl.de>
License:                     GNU GENERAL PUBLIC LICENSE
Project-URL: Repository, https://github.com/lmc297/Sismis
Project-URL: Bug Tracker, https://github.com/lmc297/Sismis/issues
Classifier: Development Status :: 4 - Beta
Classifier: Intended Audience :: Science/Research
Classifier: License :: OSI Approved :: GNU General Public License v3 (GPLv3)
Classifier: Operating System :: POSIX
Classifier: Programming Language :: Python :: 3
Classifier: Topic :: Scientific/Engineering :: Bio-Informatics
Classifier: Topic :: Scientific/Engineering :: Medical Science Apps.
Classifier: Typing :: Typed
Requires-Python: >=3.7
License-File: LICENSE
Requires-Dist: gecco~=0.10.0a3
Requires-Dist: importlib-metadata>=4.0; python_version < "3.10"
Requires-Dist: importlib-resources>=5.7; python_version < "3.11"
Dynamic: license-file
